{
    "keep": {
        "days": true,
        "amount": 14
    },
    "auditLog": "E:\\travel-agency-backend\\logs\\winston\\errors\\.eb6ad07f6694134cc257c72d751fc85335263823-audit.json",
    "files": [
        {
            "date": 1697075357510,
            "name": "E:\\travel-agency-backend\\logs\\winston\\errors\\phu-2023-12-10-04-error.log",
            "hash": "920a997285c1d5547df8a03a6d944cc5c4c87431ec147d32ae4557fb1070dfb3"
        },
        {
            "date": 1697076000543,
            "name": "E:\\travel-agency-backend\\logs\\winston\\errors\\phu-2023-12-10-05-error.log",
            "hash": "0ee8cd8a8275d4588b111c99a0a4da9dce7c5ae20ff8ba2516c4e7b05829e64f"
        },
        {
            "date": 1697079826780,
            "name": "E:\\travel-agency-backend\\logs\\winston\\errors\\phu-2023-12-10-06-error.log",
            "hash": "1ba1c9505eb098150c21709875eb4834de20f5956d95ebb14448633f2ff20d1b"
        },
        {
            "date": 1697129262315,
            "name": "E:\\travel-agency-backend\\logs\\winston\\errors\\phu-2023-12-10-19-error.log",
            "hash": "1311d10b0c9777cfcee462a5a2a84f16badc9a2713ea47f3ea5250cfba604ce3"
        },
        {
            "date": 1697130093274,
            "name": "E:\\travel-agency-backend\\logs\\winston\\errors\\phu-2023-12-10-20-error.log",
            "hash": "3252eec80e952b21c89d1b711e61a6387ac2ed4ac65328a656d4913702dbda90"
        },
        {
            "date": 1697134623972,
            "name": "E:\\travel-agency-backend\\logs\\winston\\errors\\phu-2023-12-10-21-error.log",
            "hash": "57f6366a02e4f6606f3365a456ad40e8943a3e53ec50eebd817b8278520191b9"
        },
        {
            "date": 1697137771037,
            "name": "E:\\travel-agency-backend\\logs\\winston\\errors\\phu-2023-12-10-22-error.log",
            "hash": "7fc4fdcca9f1ef1108b1b9ad7788799747ca8ca1d5796ce357b0bf7e6c9b1e87"
        },
        {
            "date": 1697209434678,
            "name": "E:\\travel-agency-backend\\logs\\winston\\errors\\phu-2023-13-10-18-error.log",
            "hash": "e38b5edfc1bfe95e64ffe444ee681d2a68e6a91757247e72dd752e6ea562891d"
        },
        {
            "date": 1697215804299,
            "name": "E:\\travel-agency-backend\\logs\\winston\\errors\\phu-2023-13-10-19-error.log",
            "hash": "ed0eec86453e189226ca46dff69309e57a6af8f60c8d7637c221941c448b02b7"
        },
        {
            "date": 1697216420234,
            "name": "E:\\travel-agency-backend\\logs\\winston\\errors\\phu-2023-13-10-20-error.log",
            "hash": "a392e3d160055ccda34cba2ac94e1bec7cbd0c3e9256764adcc2e6be8052b0a8"
        },
        {
            "date": 1697226304764,
            "name": "E:\\travel-agency-backend\\logs\\winston\\errors\\phu-2023-13-10-22-error.log",
            "hash": "6a3642072f063ffd961632c34d9156d88d09540e195754a807432ae4079382e9"
        },
        {
            "date": 1697229894891,
            "name": "E:\\travel-agency-backend\\logs\\winston\\errors\\phu-2023-13-10-23-error.log",
            "hash": "8ca9d22bac8a0f06c38657f4845b16fa669e558012e23d6c0b5812be21a53234"
        },
        {
            "date": 1697231094157,
            "name": "E:\\travel-agency-backend\\logs\\winston\\errors\\phu-2023-14-10-00-error.log",
            "hash": "4b2a16cf23ed74c0f84e66136e6a4a4f8bc95c7d7552e56c13be4a53f1ff775e"
        }
    ],
    "hashType": "sha256"
}